reeses/__init__.py
reeses/pieces.py
reeses/utils.py
reeses-0.0.2.dist-info/LICENSE
reeses-0.0.2.dist-info/METADATA
reeses-0.0.2.dist-info/WHEEL
reeses-0.0.2.dist-info/top_level.txt
reeses-0.0.2.dist-info/RECORD
