Metadata-Version: 2.1
Name: reeses
Version: 0.0.2
Summary: <_io.TextIOWrapper name='README.md' mode='r' encoding='UTF-8'>
Home-page: http://github.com/marksweissma/reeses
Author: Mark Weiss
Author-email: mark.s.weiss.ma@gmail.com
License: MIT
Platform: UNKNOWN
Requires-Dist: sklearn
Requires-Dist: numpy
